[{"docClass": "EU-fp7", "docId": "100155", "topicWeight": 0.346153846153846}, {"docClass": "EU-fp7", "docId": "100218", "topicWeight": 0.0606060606060606}, {"docClass": "EU-fp7", "docId": "100351", "topicWeight": 0.0352941176470588}, {"docClass": "EU-fp7", "docId": "100832", "topicWeight": 0.0294117647058824}, {"docClass": "EU-fp7", "docId": "101248", "topicWeight": 0.0212765957446809}, {"docClass": "EU-fp7", "docId": "102085", "topicWeight": 0.09}, {"docClass": "EU-fp7", "docId": "102289", "topicWeight": 0.131578947368421}, {"docClass": "EU-fp7", "docId": "102918", "topicWeight": 0.0875}, {"docClass": "EU-fp7", "docId": "103268", "topicWeight": 0.0425531914893617}, {"docClass": "EU-fp7", "docId": "104848", "topicWeight": 0.0357142857142857}, {"docClass": "EU-fp7", "docId": "105812", "topicWeight": 0.00934579439252336}, {"docClass": "EU-fp7", "docId": "106385", "topicWeight": 0.0317460317460317}, {"docClass": "EU-fp7", "docId": "106411", "topicWeight": 0.0555555555555556}, {"docClass": "EU-fp7", "docId": "107054", "topicWeight": 0.00847457627118644}, {"docClass": "EU-fp7", "docId": "107091", "topicWeight": 0.0606060606060606}, {"docClass": "EU-fp7", "docId": "107222", "topicWeight": 0.13}, {"docClass": "EU-fp7", "docId": "107382", "topicWeight": 0.0344827586206897}, {"docClass": "EU-fp7", "docId": "107685", "topicWeight": 0.0747663551401869}, {"docClass": "EU-fp7", "docId": "108036", "topicWeight": 0.0860215053763441}, {"docClass": "EU-fp7", "docId": "108881", "topicWeight": 0.0337078651685393}, {"docClass": "EU-fp7", "docId": "109158", "topicWeight": 0.119047619047619}, {"docClass": "EU-fp7", "docId": "109791", "topicWeight": 0.0188679245283019}, {"docClass": "EU-fp7", "docId": "109937", "topicWeight": 0.0101010101010101}, {"docClass": "EU-fp7", "docId": "111519", "topicWeight": 0.0958904109589041}, {"docClass": "EU-fp7", "docId": "111537", "topicWeight": 0.0660377358490566}, {"docClass": "EU-fp7", "docId": "111553", "topicWeight": 0.333333333333333}, {"docClass": "EU-fp7", "docId": "111591", "topicWeight": 0.0505050505050505}, {"docClass": "EU-fp7", "docId": "185619", "topicWeight": 0.157303370786517}, {"docClass": "EU-fp7", "docId": "186932", "topicWeight": 0.01}, {"docClass": "EU-fp7", "docId": "186956", "topicWeight": 0.10752688172043}, {"docClass": "EU-fp7", "docId": "187939", "topicWeight": 0.025974025974026}, {"docClass": "EU-fp7", "docId": "188187", "topicWeight": 0.0202020202020202}, {"docClass": "EU-fp7", "docId": "86786", "topicWeight": 0.186440677966102}, {"docClass": "EU-fp7", "docId": "87459", "topicWeight": 0.00943396226415094}, {"docClass": "EU-fp7", "docId": "87788", "topicWeight": 0.122448979591837}, {"docClass": "EU-fp7", "docId": "87986", "topicWeight": 0.0133333333333333}, {"docClass": "EU-fp7", "docId": "88529", "topicWeight": 0.178571428571429}, {"docClass": "EU-fp7", "docId": "88548", "topicWeight": 0.151898734177215}, {"docClass": "EU-fp7", "docId": "90277", "topicWeight": 0.0714285714285714}, {"docClass": "EU-fp7", "docId": "90913", "topicWeight": 0.131147540983607}, {"docClass": "EU-fp7", "docId": "91946", "topicWeight": 0.149425287356322}, {"docClass": "EU-fp7", "docId": "94100", "topicWeight": 0.010989010989011}, {"docClass": "EU-fp7", "docId": "94397", "topicWeight": 0.00934579439252336}, {"docClass": "EU-fp7", "docId": "95156", "topicWeight": 0.0476190476190476}, {"docClass": "EU-fp7", "docId": "96497", "topicWeight": 0.176470588235294}, {"docClass": "EU-fp7", "docId": "97516", "topicWeight": 0.0169491525423729}, {"docClass": "EU-fp7", "docId": "97867", "topicWeight": 0.0689655172413793}, {"docClass": "EU-fp7", "docId": "98023", "topicWeight": 0.025974025974026}, {"docClass": "EU-fp7", "docId": "98268", "topicWeight": 0.0102040816326531}, {"docClass": "EU-fp7", "docId": "98276", "topicWeight": 0.0188679245283019}, {"docClass": "EU-fp7", "docId": "98460", "topicWeight": 0.163636363636364}, {"docClass": "EU-fp7", "docId": "98523", "topicWeight": 0.0108695652173913}, {"docClass": "EU-fp7", "docId": "98792", "topicWeight": 0.00925925925925926}, {"docClass": "EU-fp7", "docId": "99267", "topicWeight": 0.0126582278481013}, {"docClass": "EU-fp7", "docId": "99615", "topicWeight": 0.021978021978022}, {"docClass": "EU-fp7", "docId": "99626", "topicWeight": 0.0104166666666667}, {"docClass": "EU-fp7", "docId": "99821", "topicWeight": 0.141304347826087}, {"docClass": "UK", "docId": "00291FEF-ED5D-42AE-AF73-6FD787F6CB3F", "topicWeight": 0.0306748466257669}, {"docClass": "UK", "docId": "033CFECA-07BE-49F4-9A5F-DEF6721862F4", "topicWeight": 0.130434782608696}, {"docClass": "UK", "docId": "03D7984C-7B3D-40C0-A8A1-79E6AF84172F", "topicWeight": 0.0178571428571429}, {"docClass": "UK", "docId": "03DEB8B0-15FB-49D9-B430-7C9A630E22FE", "topicWeight": 0.00909090909090909}, {"docClass": "UK", "docId": "05799965-4C53-4859-9156-FE8AE83831D7", "topicWeight": 0.0099009900990099}, {"docClass": "UK", "docId": "07B695D5-3C28-4EE6-9E02-05F84410A955", "topicWeight": 0.118343195266272}, {"docClass": "UK", "docId": "08D66E05-83BE-4370-8C8A-118D291F0C53", "topicWeight": 0.0327868852459016}, {"docClass": "UK", "docId": "08EA8ADD-7889-4974-A586-290CF299642C", "topicWeight": 0.598039215686274}, {"docClass": "UK", "docId": "0ABF39A1-9625-4D51-B07B-4CDA39AFA9E5", "topicWeight": 0.00806451612903226}, {"docClass": "UK", "docId": "0CB7A17E-CC02-4BB9-B7D7-AA9E84E8DBF3", "topicWeight": 0.0194805194805195}, {"docClass": "UK", "docId": "0CEBDC3E-229C-4D9C-9E53-756A4E047C77", "topicWeight": 0.112426035502959}, {"docClass": "UK", "docId": "0DD5CB9E-782C-493A-B4D7-541C0D083684", "topicWeight": 0.0914634146341463}, {"docClass": "UK", "docId": "0F72C5E4-2D8E-4774-829E-969AD460DF87", "topicWeight": 0.00884955752212389}, {"docClass": "UK", "docId": "0FCA1932-DA46-4A61-B0A6-725D3DEEA340", "topicWeight": 0.012987012987013}, {"docClass": "UK", "docId": "109518B5-FF1E-4BB8-9C56-EAA2D4764835", "topicWeight": 0.0216216216216216}, {"docClass": "UK", "docId": "1268F71F-C61F-444D-93B7-A20715D19DB2", "topicWeight": 0.0434782608695652}, {"docClass": "UK", "docId": "12934210-2D0D-4C01-A570-C2BA04F445B5", "topicWeight": 0.204188481675393}, {"docClass": "UK", "docId": "14769E08-5879-42D2-B05A-E78E7E6F1FD4", "topicWeight": 0.0120481927710843}, {"docClass": "UK", "docId": "15DEECB1-3DD1-451A-99F4-17C7585C0AE4", "topicWeight": 0.0175438596491228}, {"docClass": "UK", "docId": "16E89CDD-BFBD-4F04-A04E-536A56B3EB12", "topicWeight": 0.218543046357616}, {"docClass": "UK", "docId": "18B06263-ABA2-46DB-9BD5-0C8109F8CB27", "topicWeight": 0.203488372093023}, {"docClass": "UK", "docId": "1A04F550-8450-4406-840F-0DF50E59B5EE", "topicWeight": 0.037037037037037}, {"docClass": "UK", "docId": "1B02E3F6-8DAB-4906-A94B-B80068C1B834", "topicWeight": 0.178571428571429}, {"docClass": "UK", "docId": "1BE0F6BB-026D-4113-B564-EA61ED3B4B6A", "topicWeight": 0.0185185185185185}, {"docClass": "UK", "docId": "1C255179-1F4C-4FC1-A993-526F13F62F85", "topicWeight": 0.0680628272251309}, {"docClass": "UK", "docId": "1C5FFBC6-39AF-47AD-881F-8B135FE8426E", "topicWeight": 0.0209424083769634}, {"docClass": "UK", "docId": "1CE68B91-D680-48D5-A177-3357F5D465DA", "topicWeight": 0.0853658536585366}, {"docClass": "UK", "docId": "1DC4DDCF-FAA1-4E81-8E4C-6E0AE44E943B", "topicWeight": 0.133858267716535}, {"docClass": "UK", "docId": "1E1B1F6E-277F-4E92-A8CA-4707BBF32C41", "topicWeight": 0.0731707317073171}, {"docClass": "UK", "docId": "1EFA7968-FE5A-4F4E-9CC4-3E938A3C51CC", "topicWeight": 0.0552486187845304}, {"docClass": "UK", "docId": "201842D1-394A-4B8E-8551-AA6DD175A77D", "topicWeight": 0.104938271604938}, {"docClass": "UK", "docId": "20737DF6-585F-4B10-BDD7-96E429C79610", "topicWeight": 0.141414141414141}, {"docClass": "UK", "docId": "2300DF9C-BBD3-4D88-ABF3-45E710419220", "topicWeight": 0.0125786163522013}, {"docClass": "UK", "docId": "23699007-BA91-449E-883D-3E58C866D4A1", "topicWeight": 0.553398058252427}, {"docClass": "UK", "docId": "24CC3037-0F2A-474F-834D-6B27BCFE7B0A", "topicWeight": 0.0683229813664596}, {"docClass": "UK", "docId": "256066EA-F3BC-4FFE-B866-480C2A91C18A", "topicWeight": 0.0232558139534884}, {"docClass": "UK", "docId": "26551A86-147F-4FCA-9798-AFB1A9E96DD1", "topicWeight": 0.00591715976331361}, {"docClass": "UK", "docId": "274FF520-C101-46B5-A02A-CFCDA943E382", "topicWeight": 0.136094674556213}, {"docClass": "UK", "docId": "2754C6FC-6EDA-48F7-A509-1EBB9313C597", "topicWeight": 0.164102564102564}, {"docClass": "UK", "docId": "275C6EBD-F7E1-40EC-86FE-53B845014AA3", "topicWeight": 0.0229885057471264}, {"docClass": "UK", "docId": "2896A444-B0DA-4166-816B-3C960E8011D9", "topicWeight": 0.0318181818181818}, {"docClass": "UK", "docId": "28E064C4-D510-414F-859A-B2275784A741", "topicWeight": 0.0272727272727273}, {"docClass": "UK", "docId": "2991FAB6-9F56-4D00-9060-D30BD136E782", "topicWeight": 0.222222222222222}, {"docClass": "UK", "docId": "2A486A05-D649-43CE-AC24-973718C1E5B3", "topicWeight": 0.0575916230366492}, {"docClass": "UK", "docId": "2AF7F9CB-FF3C-4AAC-B711-C8E7FAB6E771", "topicWeight": 0.0209424083769634}, {"docClass": "UK", "docId": "2B5C7DCC-154E-462D-B141-EA7E37E1C7C8", "topicWeight": 0.0124223602484472}, {"docClass": "UK", "docId": "2CD917C4-0015-4451-9B31-0FEBAF778635", "topicWeight": 0.0177514792899408}, {"docClass": "UK", "docId": "2D1C7024-6237-4702-9E7F-4A9A610DAF1D", "topicWeight": 0.0642201834862385}, {"docClass": "UK", "docId": "2F6E3DFD-C900-434D-9F02-A7F59C5ADA37", "topicWeight": 0.0785340314136126}, {"docClass": "UK", "docId": "3017A355-64F6-4377-9C46-1BDB17930420", "topicWeight": 0.282485875706215}, {"docClass": "UK", "docId": "31B284A9-E764-4FB3-9DFF-9FA3D71ACF65", "topicWeight": 0.028735632183908}, {"docClass": "UK", "docId": "322B627F-3A8B-4F70-9C1D-8AD1D5D6BD0F", "topicWeight": 0.00961538461538462}, {"docClass": "UK", "docId": "32C32251-9350-41EF-A720-5B824CE41575", "topicWeight": 0.120689655172414}, {"docClass": "UK", "docId": "32C8A953-D42D-49C6-B60B-A6CEED82D76A", "topicWeight": 0.0476190476190476}, {"docClass": "UK", "docId": "3370CA59-BCB6-4A45-829F-61408608E32D", "topicWeight": 0.0958083832335329}, {"docClass": "UK", "docId": "37EE049B-A401-4F03-8699-B911F499ADA4", "topicWeight": 0.0114285714285714}, {"docClass": "UK", "docId": "3984F019-C6EC-4C64-BFD2-D1C8FCB41E14", "topicWeight": 0.137404580152672}, {"docClass": "UK", "docId": "3A387A89-1343-4DD7-93C2-95651BF8D48B", "topicWeight": 0.0685714285714286}, {"docClass": "UK", "docId": "3B74634A-5E0D-42A3-A865-7353B4CF4052", "topicWeight": 0.0903225806451613}, {"docClass": "UK", "docId": "3C77649A-9D16-4B06-A925-D90F61F9CD9E", "topicWeight": 0.0793650793650794}, {"docClass": "UK", "docId": "3D2B2CDA-D7EC-4502-BCF5-7E70B985D968", "topicWeight": 0.231788079470199}, {"docClass": "UK", "docId": "3DEA10F1-C4B1-47D2-AC3A-A55A5DB712CF", "topicWeight": 0.138364779874214}, {"docClass": "UK", "docId": "40C911A7-5741-4581-976C-351B120D545D", "topicWeight": 0.165562913907285}, {"docClass": "UK", "docId": "40F94FED-7126-42A2-8144-01D0AF17FAA0", "topicWeight": 0.0597014925373134}, {"docClass": "UK", "docId": "426178FF-C2FB-4174-8BD3-2034EF917D0F", "topicWeight": 0.0706521739130435}, {"docClass": "UK", "docId": "42CC63BB-7464-43EF-B38E-6958A25F876A", "topicWeight": 0.0648148148148148}, {"docClass": "UK", "docId": "4309B136-6CE4-4891-AA67-7FE745EB72D9", "topicWeight": 0.18}, {"docClass": "UK", "docId": "443AD127-C286-45E3-A9A4-4534EC090254", "topicWeight": 0.0179640718562874}, {"docClass": "UK", "docId": "443EE781-233D-4810-9723-BEBDCB4DEFB1", "topicWeight": 0.0538922155688623}, {"docClass": "UK", "docId": "44F22AAD-C8CB-4933-836B-5850B28C5A6B", "topicWeight": 0.0538461538461538}, {"docClass": "UK", "docId": "450C51B9-B1BC-4806-A286-46A19CABE5D2", "topicWeight": 0.193548387096774}, {"docClass": "UK", "docId": "4A7CC293-320A-40EA-A10D-22770137CD42", "topicWeight": 0.0890052356020942}, {"docClass": "UK", "docId": "4AC31CBC-D776-44F1-AB56-CAADEFCBF4EB", "topicWeight": 0.00636942675159236}, {"docClass": "UK", "docId": "4B35EC61-072C-4E3A-BB92-20F470620094", "topicWeight": 0.126506024096386}, {"docClass": "UK", "docId": "4CC05AAC-B1E4-450A-936F-AFE5B5057059", "topicWeight": 0.0111111111111111}, {"docClass": "UK", "docId": "4D07116F-7B35-461C-9B7A-E123793F5104", "topicWeight": 0.0119760479041916}, {"docClass": "UK", "docId": "4EF7F2A8-71FD-4F84-BC84-61E185797BDF", "topicWeight": 0.213235294117647}, {"docClass": "UK", "docId": "4F467483-E917-4246-8197-F881649EAA4A", "topicWeight": 0.12}, {"docClass": "UK", "docId": "4F8DED1D-78F4-465A-8F2D-CC95EE6F45C3", "topicWeight": 0.0429447852760736}, {"docClass": "UK", "docId": "4FD36857-061F-402A-BA39-93FCD914430D", "topicWeight": 0.0337078651685393}, {"docClass": "UK", "docId": "50037419-BB5D-42C7-AEDD-D9AF541D01B3", "topicWeight": 0.188888888888889}, {"docClass": "UK", "docId": "52644363-EE23-489D-AD08-28FD97EBE24F", "topicWeight": 0.283018867924528}, {"docClass": "UK", "docId": "52C90E17-67E1-4A28-B9BA-27575B12990E", "topicWeight": 0.0285714285714286}, {"docClass": "UK", "docId": "5303B106-EEB7-4A1F-A242-2585C16CF6D0", "topicWeight": 0.00515463917525773}, {"docClass": "UK", "docId": "5392EAE0-DF01-4DE0-8AA1-F99049262DBA", "topicWeight": 0.04}, {"docClass": "UK", "docId": "53D31F8B-8B07-4E4C-849A-29C2A9AE5035", "topicWeight": 0.0540540540540541}, {"docClass": "UK", "docId": "56377702-A366-4CF2-9A53-604CE4D6F60F", "topicWeight": 0.0366492146596859}, {"docClass": "UK", "docId": "57100F12-0A40-4919-85C6-F37E7A762EAD", "topicWeight": 0.0842696629213483}, {"docClass": "UK", "docId": "573EB86D-4882-421D-BE05-507BF2F35CE7", "topicWeight": 0.0202020202020202}, {"docClass": "UK", "docId": "5747D8D6-2E6F-4563-853E-38B095DA116A", "topicWeight": 0.2}, {"docClass": "UK", "docId": "579F43A6-CCEB-4058-BEEB-9803472F0A5A", "topicWeight": 0.215686274509804}, {"docClass": "UK", "docId": "57B9DBA6-633D-49F4-81AA-4D82EDF2A495", "topicWeight": 0.0754716981132075}, {"docClass": "UK", "docId": "57C0CD6D-91BB-4ECD-B298-5083F0EF58C2", "topicWeight": 0.0697674418604651}, {"docClass": "UK", "docId": "59CD97AC-D947-4A34-84DB-F1D5C05EA6EF", "topicWeight": 0.00735294117647059}, {"docClass": "UK", "docId": "5AD37717-D74A-4089-9276-E33829860CDA", "topicWeight": 0.0158730158730159}, {"docClass": "UK", "docId": "5B7940A6-309C-472D-B962-16078DC75D2A", "topicWeight": 0.0887573964497041}, {"docClass": "UK", "docId": "5BAEA0FD-A018-413F-9EB9-6C6D47AB5A68", "topicWeight": 0.324561403508772}, {"docClass": "UK", "docId": "5C3D0F05-285B-4C00-9797-C0065EED9BB6", "topicWeight": 1}, {"docClass": "UK", "docId": "5C46298E-FE86-4D69-BEF5-00C0AF66BBA0", "topicWeight": 0.036036036036036}, {"docClass": "UK", "docId": "5D3A4E55-9721-4FFF-AA8D-8D7ACBC31293", "topicWeight": 0.0747663551401869}, {"docClass": "UK", "docId": "5D825BA9-782B-45D8-9EB6-30C7B99ABFC9", "topicWeight": 0.112244897959184}, {"docClass": "UK", "docId": "5DB40F66-0174-4193-A2E1-8DAFC06A6711", "topicWeight": 0.0194174757281553}, {"docClass": "UK", "docId": "5DBCAE69-A715-40AD-97A7-33D08F8E34F9", "topicWeight": 0.0777777777777778}, {"docClass": "UK", "docId": "5F3AE904-2B28-4A96-B1AA-64BEE3BF5C05", "topicWeight": 0.0174418604651163}, {"docClass": "UK", "docId": "60006FB2-066C-4A36-98BA-A38CB25A5D1F", "topicWeight": 0.00819672131147541}, {"docClass": "UK", "docId": "6001B0EE-8A69-4AA8-89C0-88AF1D45E9DC", "topicWeight": 0.0851063829787234}, {"docClass": "UK", "docId": "60473663-14E5-43C3-8458-1B493FEB0137", "topicWeight": 0.0138888888888889}, {"docClass": "UK", "docId": "608C6C10-BE27-46F1-B391-DD67270F6407", "topicWeight": 0.235294117647059}, {"docClass": "UK", "docId": "6094706A-D81D-4C2C-803B-7B2ED5843DDA", "topicWeight": 0.18796992481203}, {"docClass": "UK", "docId": "60C56827-8F12-48E7-8AEF-B08C8D4820AD", "topicWeight": 0.046242774566474}, {"docClass": "UK", "docId": "62A62677-689B-41B4-8648-208DA00643A9", "topicWeight": 0.00510204081632653}, {"docClass": "UK", "docId": "62FC93F0-E643-4791-B830-36506DC82552", "topicWeight": 0.036036036036036}, {"docClass": "UK", "docId": "631E694A-20AE-4E52-9EC3-BF56481C9BB1", "topicWeight": 0.186206896551724}, {"docClass": "UK", "docId": "63B55923-6E68-4ACD-B1CF-B0D941665F19", "topicWeight": 0.192982456140351}, {"docClass": "UK", "docId": "643A319F-0A21-4F3C-86E9-804CD43DC37A", "topicWeight": 0.0523809523809524}, {"docClass": "UK", "docId": "64FD18FA-F92B-4F7F-96BB-3E2D24455D3F", "topicWeight": 0.212121212121212}, {"docClass": "UK", "docId": "66CB0696-F738-4139-B9F7-040E24AC9BA8", "topicWeight": 0.1}, {"docClass": "UK", "docId": "69890AA7-120A-4229-B8E2-B05999CD9BD3", "topicWeight": 0.00432900432900433}, {"docClass": "UK", "docId": "6BD16044-4DEA-4BAD-A75A-255A3FAFE894", "topicWeight": 0.0670103092783505}, {"docClass": "UK", "docId": "6BD6DF59-41DD-4687-8FCE-46B5714D315E", "topicWeight": 0.020979020979021}, {"docClass": "UK", "docId": "6C6EA4D5-26D8-40C5-B41F-E447A69F520F", "topicWeight": 0.243243243243243}, {"docClass": "UK", "docId": "6CC0848D-F9A3-4A91-B7F9-5B76427A9ADC", "topicWeight": 0.031413612565445}, {"docClass": "UK", "docId": "6CEE683E-AC9B-4DEC-9842-DDE4B7F6FC1B", "topicWeight": 0.0412371134020619}, {"docClass": "UK", "docId": "6D2F92E9-5B92-45A0-8075-663CA6D6C727", "topicWeight": 0.0326797385620915}, {"docClass": "UK", "docId": "701FC58D-E906-43EA-9447-FF8E73D0F26F", "topicWeight": 0.0172413793103448}, {"docClass": "UK", "docId": "708C7706-47FF-4F10-B1AA-42F8F03AC923", "topicWeight": 0.0154639175257732}, {"docClass": "UK", "docId": "741D2A48-FEBF-4AFB-AE86-6A920771EC74", "topicWeight": 0.0454545454545455}, {"docClass": "UK", "docId": "74272D07-E360-46F6-968B-A1C6C6167A27", "topicWeight": 0.0386473429951691}, {"docClass": "UK", "docId": "7540E856-8B04-4DEB-B30F-4FDA3B68F180", "topicWeight": 0.284090909090909}, {"docClass": "UK", "docId": "7702222C-4E0F-4D4A-9A0E-7F7BF2EFA85B", "topicWeight": 0.0434782608695652}, {"docClass": "UK", "docId": "778358BF-1338-46F5-9E4C-09051CC00BEE", "topicWeight": 0.0155440414507772}, {"docClass": "UK", "docId": "787CAFCC-F917-4266-8560-131AA5086A71", "topicWeight": 0.149425287356322}, {"docClass": "UK", "docId": "78B1F963-2764-4935-BA96-D538E69D29EE", "topicWeight": 0.016260162601626}, {"docClass": "UK", "docId": "7952E65C-D3B7-41B2-9743-D7C8A7E19E1A", "topicWeight": 0.186046511627907}, {"docClass": "UK", "docId": "795D5F37-B09A-49C6-8BD2-A8B45958451E", "topicWeight": 0.00970873786407767}, {"docClass": "UK", "docId": "79C12DDD-F436-4CA9-9E3B-060AAFF4A632", "topicWeight": 0.183823529411765}, {"docClass": "UK", "docId": "7B0A67E8-AA12-46F6-BC77-34B47B58F94D", "topicWeight": 0.0388888888888889}, {"docClass": "UK", "docId": "7B8A9C63-3B38-4897-940B-88973FDB8611", "topicWeight": 0.0275229357798165}, {"docClass": "UK", "docId": "7C726B67-11CD-4363-A386-D411DC26C863", "topicWeight": 0.0552147239263804}, {"docClass": "UK", "docId": "7F333A2D-79CB-4485-B8B1-5BFC40630804", "topicWeight": 0.0133333333333333}, {"docClass": "UK", "docId": "7F58DCD1-3074-4E71-BB76-C71439C6CE97", "topicWeight": 0.031055900621118}, {"docClass": "UK", "docId": "7FDB0DF5-A2AB-479F-BA79-66D14F0FB7BC", "topicWeight": 0.0292397660818713}, {"docClass": "UK", "docId": "80C897C4-9B93-4A99-A8F3-DDC04580812A", "topicWeight": 0.157894736842105}, {"docClass": "UK", "docId": "8185CF7A-5FD7-42C9-A0E0-EAF9DF2D011A", "topicWeight": 0.0336134453781513}, {"docClass": "UK", "docId": "82707E74-38EC-43F3-BD33-883A072EDB04", "topicWeight": 0.0198675496688742}, {"docClass": "UK", "docId": "83DBB2E3-64AD-4EA9-8AC1-DF7DC1B90486", "topicWeight": 0.0543478260869565}, {"docClass": "UK", "docId": "84FD0385-BBBC-4068-A68B-5C55F6AFCB16", "topicWeight": 0.25}, {"docClass": "UK", "docId": "85F142D3-9096-448B-A21C-B064930E870E", "topicWeight": 0.0740740740740741}, {"docClass": "UK", "docId": "862ACAB7-BEDF-4EB2-977F-B6B324726FA4", "topicWeight": 0.166666666666667}, {"docClass": "UK", "docId": "87CE48C9-8DEE-4266-9A9D-A7B076B834AC", "topicWeight": 0.111111111111111}, {"docClass": "UK", "docId": "881E5935-B47D-4EF0-8B2E-3FE68166AC7B", "topicWeight": 0.183098591549296}, {"docClass": "UK", "docId": "8B1E402B-E52D-4ABA-8D79-64DDD18E7BAE", "topicWeight": 0.0740740740740741}, {"docClass": "UK", "docId": "8B3B4436-29DC-47F4-83D5-5DA4C39166A3", "topicWeight": 0.0282485875706215}, {"docClass": "UK", "docId": "8B41C749-C3C2-4969-8CBA-783AFB2FC020", "topicWeight": 0.0582010582010582}, {"docClass": "UK", "docId": "8BCF1DB4-64E8-4002-AC1F-6EEA3C363A37", "topicWeight": 0.112781954887218}, {"docClass": "UK", "docId": "8EA809E1-03F2-4738-8505-D43E53527EE7", "topicWeight": 0.0258064516129032}, {"docClass": "UK", "docId": "8EF6A332-4F59-496F-A6D5-19CDAB530137", "topicWeight": 0.18796992481203}, {"docClass": "UK", "docId": "8FE96F96-84B1-4B03-8E40-2A38CF935852", "topicWeight": 0.00657894736842105}, {"docClass": "UK", "docId": "904D38EA-6E44-4578-833B-26ED40E4C3E7", "topicWeight": 0.170454545454545}, {"docClass": "UK", "docId": "9152AC16-73F6-4B0A-BC62-BD409057A904", "topicWeight": 0.0104166666666667}, {"docClass": "UK", "docId": "91A4CA5C-8F50-4330-8F07-8703A21B0D3D", "topicWeight": 0.00546448087431694}, {"docClass": "UK", "docId": "9274F5A0-9016-4489-9AC6-1257502D2568", "topicWeight": 0.0142857142857143}, {"docClass": "UK", "docId": "92A7D814-8A1B-4877-90B3-6501B7F091B6", "topicWeight": 0.101010101010101}, {"docClass": "UK", "docId": "92BD5450-E9CF-4D0E-BC93-CCB74D263A9E", "topicWeight": 0.0160427807486631}, {"docClass": "UK", "docId": "938131A2-B82A-465F-A1E5-EA04003D8C29", "topicWeight": 0.04}, {"docClass": "UK", "docId": "94AA2020-7A0D-44EA-87A2-FCD4EAFD2042", "topicWeight": 0.147058823529412}, {"docClass": "UK", "docId": "963FF637-A7A9-4FF7-869A-42D8F054E4A8", "topicWeight": 0.00854700854700855}, {"docClass": "UK", "docId": "968064B9-F6DE-4AD4-9E4E-D3F587EB2CC8", "topicWeight": 0.122270742358079}, {"docClass": "UK", "docId": "96AE3F57-03B4-41DA-B69F-59A891CD9364", "topicWeight": 0.0153846153846154}, {"docClass": "UK", "docId": "96B0C4DB-7706-405D-A863-7B459D9E60A3", "topicWeight": 0.0186915887850467}, {"docClass": "UK", "docId": "96B2C17F-8642-406A-AD62-BBC0DFC942EC", "topicWeight": 0.0578947368421053}, {"docClass": "UK", "docId": "96D10FBF-1A49-4483-BC08-DF852B7DC4BD", "topicWeight": 0.193181818181818}, {"docClass": "UK", "docId": "9703DB7C-6AA9-4C99-85A6-4E358CC064BD", "topicWeight": 0.0645161290322581}, {"docClass": "UK", "docId": "9758407A-2F3E-46A5-8517-BECAEB49D2A4", "topicWeight": 0.127388535031847}, {"docClass": "UK", "docId": "97CA3447-97C1-428B-85A2-5F4B516BB2B3", "topicWeight": 0.159090909090909}, {"docClass": "UK", "docId": "9856594D-8B7D-485C-BCE2-B23A3CC2F2BA", "topicWeight": 0.00680272108843537}, {"docClass": "UK", "docId": "988CBAAF-5AE4-4C30-BA43-EE11716019FB", "topicWeight": 0.213114754098361}, {"docClass": "UK", "docId": "98B6CB11-7B6F-4AAC-A886-4AE7C8728466", "topicWeight": 0.0833333333333333}, {"docClass": "UK", "docId": "98E1EA18-E7EA-44D2-9515-045AC5EDD3F1", "topicWeight": 0.0826446280991736}, {"docClass": "UK", "docId": "9A82EB9A-0C3E-4078-B1F4-B41D12C73342", "topicWeight": 0.0364583333333333}, {"docClass": "UK", "docId": "9AE9B7BB-BBAA-4BC5-AAE6-C6BAB6C2E06B", "topicWeight": 0.0208333333333333}, {"docClass": "UK", "docId": "9B251913-9C56-403A-AB87-053A8FC75DCC", "topicWeight": 0.0676691729323308}, {"docClass": "UK", "docId": "9C4FF96C-E96F-4714-B914-332D552CE9BF", "topicWeight": 0.0192307692307692}, {"docClass": "UK", "docId": "9D035099-ADEF-43DB-B51A-33177B8868BA", "topicWeight": 0.0575539568345324}, {"docClass": "UK", "docId": "9D87B6C1-6524-4F54-B9D7-EF6D111CD6B7", "topicWeight": 0.2}, {"docClass": "UK", "docId": "9F57F86D-D412-42A4-A614-3EBA90BEFDB2", "topicWeight": 0.00495049504950495}, {"docClass": "UK", "docId": "9FB66FC5-7630-4326-B359-0AB42E06FE82", "topicWeight": 0.1}, {"docClass": "UK", "docId": "A014AFC5-1A53-4A2D-9F4F-1E2439E8ADA6", "topicWeight": 0.533980582524272}, {"docClass": "UK", "docId": "A07E3A1E-E2FB-44F5-9BE6-FB93F7AA9CB8", "topicWeight": 0.0694444444444444}, {"docClass": "UK", "docId": "A09CB1FF-FD9F-4412-811E-AC81C9E03139", "topicWeight": 0.00505050505050505}, {"docClass": "UK", "docId": "A0F534F9-246E-4315-AB04-2F2A3CAAE384", "topicWeight": 0.00917431192660551}, {"docClass": "UK", "docId": "A1896DCF-CE43-4A5A-A18F-C55F9EAA53E5", "topicWeight": 0.372881355932203}, {"docClass": "UK", "docId": "A1AAF9C0-7DBE-4D46-A514-E29798CA1CDF", "topicWeight": 0.0153846153846154}, {"docClass": "UK", "docId": "A2A0A74F-3CFB-43C8-A2D1-47D2CCF43336", "topicWeight": 0.0787878787878788}, {"docClass": "UK", "docId": "A367690B-37CC-47D7-A282-E29DA61D90D5", "topicWeight": 0.00943396226415094}, {"docClass": "UK", "docId": "A36F38E4-5F87-4D0B-930B-9DFCD0B53B04", "topicWeight": 0.0357142857142857}, {"docClass": "UK", "docId": "A457814C-D498-4E03-AEA0-3F0A9A804B70", "topicWeight": 0.0745341614906832}, {"docClass": "UK", "docId": "A47E29A6-1FFA-4AC5-9244-787BF556261B", "topicWeight": 0.0454545454545455}, {"docClass": "UK", "docId": "A6088574-0E50-427A-A568-FBBB9332361A", "topicWeight": 0.0217391304347826}, {"docClass": "UK", "docId": "A655AC46-0E43-4BC7-95E7-C1E64C8A13A9", "topicWeight": 0.0261780104712042}, {"docClass": "UK", "docId": "A82AFAAA-8020-4E29-8F42-B57D1957438D", "topicWeight": 0.0206896551724138}, {"docClass": "UK", "docId": "A880C28A-AFD7-4FE8-9818-75A1EEE58AB5", "topicWeight": 0.155844155844156}, {"docClass": "UK", "docId": "A8992DA3-F92E-4700-AD77-8C80AEA46A50", "topicWeight": 0.0903225806451613}, {"docClass": "UK", "docId": "A9BEECE8-C44D-4BFC-9257-E09636A65EB5", "topicWeight": 0.123076923076923}, {"docClass": "UK", "docId": "AA221F63-A7D2-4371-916F-F3E139900086", "topicWeight": 0.0699300699300699}, {"docClass": "UK", "docId": "AB076734-4355-4FCC-9B98-6D6B44BE7C96", "topicWeight": 0.0207253886010363}, {"docClass": "UK", "docId": "AB591873-40E4-4CA5-83CC-A6311E9E499C", "topicWeight": 0.112299465240642}, {"docClass": "UK", "docId": "AB83589A-B0FA-4C07-9D68-6063C5B9E094", "topicWeight": 0.0263157894736842}, {"docClass": "UK", "docId": "AB9555B6-116F-4BE0-A667-4C31922182BA", "topicWeight": 0.111111111111111}, {"docClass": "UK", "docId": "ABC00B58-B0FC-4866-9B12-48B2AE0A8988", "topicWeight": 0.147826086956522}, {"docClass": "UK", "docId": "AC241B48-9146-4452-9986-0F7433DF9BF4", "topicWeight": 0.00546448087431694}, {"docClass": "UK", "docId": "AC744268-037A-458A-8659-2DCF0648AE7F", "topicWeight": 0.491935483870968}, {"docClass": "UK", "docId": "ACDD0FC1-3A11-4B61-8D02-68D9808DEE03", "topicWeight": 0.037037037037037}, {"docClass": "UK", "docId": "AD1D141D-331E-4C49-A598-DAFA98236E7C", "topicWeight": 0.0220588235294118}, {"docClass": "UK", "docId": "AD967C21-9316-4D60-BACD-9CC89940D60C", "topicWeight": 0.019047619047619}, {"docClass": "UK", "docId": "AE0BE06C-5C10-437E-90B3-D995D87D4005", "topicWeight": 0.032258064516129}, {"docClass": "UK", "docId": "AE5A7040-A133-47C5-9E4F-8EBA0430232F", "topicWeight": 0.0216216216216216}, {"docClass": "UK", "docId": "B003EF3B-4941-4A6E-9D8D-1AB0BE415EBD", "topicWeight": 0.0111111111111111}, {"docClass": "UK", "docId": "B0254F81-3A6C-4826-83EF-DB90B6D7B7EC", "topicWeight": 0.179640718562874}, {"docClass": "UK", "docId": "B0AA095F-6C89-4F9D-B174-99FFB1A7E240", "topicWeight": 0.25}, {"docClass": "UK", "docId": "B1476B43-3C99-4189-9A52-D8B89F7B8953", "topicWeight": 0.0701754385964912}, {"docClass": "UK", "docId": "B16DE9AF-7619-4C3A-975F-9BE5DB84C9C1", "topicWeight": 0.0689655172413793}, {"docClass": "UK", "docId": "B289DC30-70C8-43B0-8D11-29702AF7DFA3", "topicWeight": 0.10077519379845}, {"docClass": "UK", "docId": "B3BD6482-6DFB-49CC-9E48-1358663AF7CF", "topicWeight": 0.0581395348837209}, {"docClass": "UK", "docId": "B4C12CD6-384D-44D5-8A78-2ACCA0AB3946", "topicWeight": 1}, {"docClass": "UK", "docId": "B4CA6C0D-A05C-4EDE-B786-EA36837C21CD", "topicWeight": 0.00943396226415094}, {"docClass": "UK", "docId": "B4F88BE7-2FAA-4344-B82A-FA705F85B650", "topicWeight": 0.0254777070063694}, {"docClass": "UK", "docId": "B60085D2-6440-44E4-A992-B0954ECBCC34", "topicWeight": 0.0161290322580645}, {"docClass": "UK", "docId": "B67E6194-6A1B-4341-BD86-394D012F9DC7", "topicWeight": 0.0133333333333333}, {"docClass": "UK", "docId": "B850AD61-6B04-4227-A677-183545D87D32", "topicWeight": 0.0109289617486339}, {"docClass": "UK", "docId": "B85F5C64-A989-4E4D-93AD-84256C942A53", "topicWeight": 0.0564516129032258}, {"docClass": "UK", "docId": "B88C3041-188C-4A95-A3E5-CE15F5BC35CA", "topicWeight": 0.10062893081761}, {"docClass": "UK", "docId": "B89D554A-48A6-4991-BC90-D47E024D54CC", "topicWeight": 0.0240963855421687}, {"docClass": "UK", "docId": "B89F7161-4F5C-452E-841C-7047000BD408", "topicWeight": 0.245283018867925}, {"docClass": "UK", "docId": "B98DEACB-B4EB-4632-8477-0C0AE53F7E02", "topicWeight": 0.0578034682080925}, {"docClass": "UK", "docId": "BA187187-4CEF-4481-87C4-4BC20FDA982E", "topicWeight": 0.00694444444444444}, {"docClass": "UK", "docId": "BA52A266-9473-43CC-91A1-4678C8C24CB8", "topicWeight": 0.0238095238095238}, {"docClass": "UK", "docId": "BA6A3D23-C51B-46CA-9518-FE58D6256DA8", "topicWeight": 0.0645161290322581}, {"docClass": "UK", "docId": "BA9C9C28-2841-4A3C-B1D5-522FF63FC2AC", "topicWeight": 0.00694444444444444}, {"docClass": "UK", "docId": "BAACAF9C-41FB-45C6-B234-2CCBA9037DD2", "topicWeight": 0.795454545454545}, {"docClass": "UK", "docId": "BB0A4662-4048-45A2-BB7B-FD59292F9D34", "topicWeight": 0.148648648648649}, {"docClass": "UK", "docId": "BBB05A32-7590-4AF4-B949-8B01F8D8356C", "topicWeight": 0.0285714285714286}, {"docClass": "UK", "docId": "BC2639D5-86F5-4AD3-82E6-977425152BF6", "topicWeight": 0.0357142857142857}, {"docClass": "UK", "docId": "BC6B5694-AD56-434F-8CC9-C281C119D66E", "topicWeight": 0.0467289719626168}, {"docClass": "UK", "docId": "BCD38564-63EF-4FC2-8E77-640825E6C321", "topicWeight": 0.112903225806452}, {"docClass": "UK", "docId": "BCFDA6B8-FF9E-4ADB-B153-E6624FDA7D55", "topicWeight": 0.0256410256410256}, {"docClass": "UK", "docId": "BE11F6D5-E20C-4320-A296-2F8FBF406F81", "topicWeight": 0.239130434782609}, {"docClass": "UK", "docId": "BE634249-0304-4B23-BC1A-79403656572A", "topicWeight": 0.0169491525423729}, {"docClass": "UK", "docId": "BFCF32DF-FC40-474D-A5B1-B47A3370A90B", "topicWeight": 0.25}, {"docClass": "UK", "docId": "BFDE672B-6AB9-4EC6-9FC0-63494EBFAAE5", "topicWeight": 0.288770053475936}, {"docClass": "UK", "docId": "C0364EB5-7117-4CCB-92D6-956EAC33336A", "topicWeight": 0.25}, {"docClass": "UK", "docId": "C04BF265-4EFD-49EE-AD4E-7D0217BBF445", "topicWeight": 0.181818181818182}, {"docClass": "UK", "docId": "C06C11D3-3D8A-4ADD-BDDA-A679509C0510", "topicWeight": 0.0113636363636364}, {"docClass": "UK", "docId": "C0957E57-3F00-4294-93B7-05D7F5E3ACE4", "topicWeight": 0.0344827586206897}, {"docClass": "UK", "docId": "C0A4D026-B65A-40BD-8524-10154416B009", "topicWeight": 0.0683760683760684}, {"docClass": "UK", "docId": "C12EA587-7BBC-4D74-BA07-6320BB15FDF4", "topicWeight": 0.0207253886010363}, {"docClass": "UK", "docId": "C13CA898-90E0-408A-BB21-FC21AD735843", "topicWeight": 0.306818181818182}, {"docClass": "UK", "docId": "C1C82010-C840-400E-B8F3-B06E7314FFD5", "topicWeight": 0.0454545454545455}, {"docClass": "UK", "docId": "C224343C-9FDB-4D82-825B-481023914D52", "topicWeight": 0.0143540669856459}, {"docClass": "UK", "docId": "C2915683-517F-46E9-B1EF-4F83BF76CD38", "topicWeight": 0.0481283422459893}, {"docClass": "UK", "docId": "C2C20771-081D-47DB-8BE9-9D1C4E655D0F", "topicWeight": 0.1}, {"docClass": "UK", "docId": "C3A807B0-D562-4CC2-A3C6-BE40E4BB607A", "topicWeight": 0.0774193548387097}, {"docClass": "UK", "docId": "C4ACC177-61A0-48CC-AFB8-CB1E3ED78C5A", "topicWeight": 0.010752688172043}, {"docClass": "UK", "docId": "C64570C0-A068-4002-8EE7-49C59D40CF51", "topicWeight": 0.012987012987013}, {"docClass": "UK", "docId": "C691FF0F-5489-4B09-BC3E-DBDE253AFB9D", "topicWeight": 0.0158730158730159}, {"docClass": "UK", "docId": "C720EEE5-1AE0-449D-86FE-62B76D025EBB", "topicWeight": 0.00694444444444444}, {"docClass": "UK", "docId": "C7431B77-053A-4E22-AECF-2438E220301D", "topicWeight": 0.0128205128205128}, {"docClass": "UK", "docId": "C853EEBE-95FF-4FE1-ACEA-7913C82F75E7", "topicWeight": 0.0515463917525773}, {"docClass": "UK", "docId": "C8BD9069-1102-4429-9753-0A2B96BC7DBC", "topicWeight": 0.0552486187845304}, {"docClass": "UK", "docId": "C90457F0-81ED-4F1F-BB69-28F7CD56AC77", "topicWeight": 0.138888888888889}, {"docClass": "UK", "docId": "C90CDD44-0775-4859-8833-E96CA8DBF0DA", "topicWeight": 0.196850393700787}, {"docClass": "UK", "docId": "CA28FD29-1649-41E3-A047-C4A006CC8DA9", "topicWeight": 0.0517241379310345}, {"docClass": "UK", "docId": "CA58BFF0-82F9-4290-A484-9BA95E9C0686", "topicWeight": 0.00869565217391304}, {"docClass": "UK", "docId": "CA6931A8-107A-4902-9228-5CBE6C864771", "topicWeight": 0.0256410256410256}, {"docClass": "UK", "docId": "CB48358A-0F17-4DDA-B6E3-57AA4B40ACB6", "topicWeight": 0.0440251572327044}, {"docClass": "UK", "docId": "CB77D6EB-BBF0-4FD0-B82C-42636F0E5AB9", "topicWeight": 0.196428571428571}, {"docClass": "UK", "docId": "CB994515-FF65-402E-A379-885E17D2FBD6", "topicWeight": 0.680555555555556}, {"docClass": "UK", "docId": "CBC22D07-C1A1-415D-84C9-36AAE3547EA8", "topicWeight": 0.590909090909091}, {"docClass": "UK", "docId": "CCD977B0-77BC-4514-90A4-422E1DD37873", "topicWeight": 0.0645161290322581}, {"docClass": "UK", "docId": "CE3DA096-9E07-4F78-98C9-A765906F2659", "topicWeight": 0.128654970760234}, {"docClass": "UK", "docId": "CF2B1C5C-9DD3-4238-8950-01EBA73CB5DD", "topicWeight": 0.12280701754386}, {"docClass": "UK", "docId": "CF714117-BE39-4690-8312-6D12BF362FD9", "topicWeight": 0.0147058823529412}, {"docClass": "UK", "docId": "CFDAC175-492C-4333-908F-270E5C3FB8AF", "topicWeight": 0.12962962962963}, {"docClass": "UK", "docId": "D03BBB27-BCF2-4044-8D53-D762B979AA8F", "topicWeight": 0.0175438596491228}, {"docClass": "UK", "docId": "D044489B-ACE9-4A1C-8CC1-1CD6C571D021", "topicWeight": 0.416666666666667}, {"docClass": "UK", "docId": "D5001053-7DBA-4949-AA1F-1FFF8D0ED6D9", "topicWeight": 0.0677966101694915}, {"docClass": "UK", "docId": "D590225D-1B8E-4594-A45B-8A4EDC304FF2", "topicWeight": 0.162650602409639}, {"docClass": "UK", "docId": "D5DECF64-F6CB-4CD2-9F0B-6FA94687E9C3", "topicWeight": 0.00628930817610063}, {"docClass": "UK", "docId": "D606C000-A1C4-44C8-A10E-2E70E94B24C6", "topicWeight": 0.0141843971631206}, {"docClass": "UK", "docId": "D61B14FA-C82A-402F-9F7C-1705C0724DA5", "topicWeight": 0.04}, {"docClass": "UK", "docId": "D6ACD6BE-6220-45D3-9672-5F88A65B6209", "topicWeight": 0.128491620111732}, {"docClass": "UK", "docId": "D7F328E4-2EFF-49D0-A164-786F2CD74FE5", "topicWeight": 0.0272727272727273}, {"docClass": "UK", "docId": "D863BCCA-6E9F-486C-8F23-D0C8FFE52A5B", "topicWeight": 0.112903225806452}, {"docClass": "UK", "docId": "D8C415A5-A34A-44B6-B870-D3F0857FA190", "topicWeight": 0.021978021978022}, {"docClass": "UK", "docId": "D8FB7941-C102-487D-B918-D054B242D091", "topicWeight": 0.243243243243243}, {"docClass": "UK", "docId": "D96C8DDC-523F-49E4-950B-D0081D656B40", "topicWeight": 0.194444444444444}, {"docClass": "UK", "docId": "D9F7B3AF-5582-4901-9DB7-69B0B0655A80", "topicWeight": 0.13265306122449}, {"docClass": "UK", "docId": "DAF2A0E5-A9C0-4BBE-8FA4-85C3810E0817", "topicWeight": 0.12037037037037}, {"docClass": "UK", "docId": "DB12B677-E236-4CF2-A1D8-DAD31D246582", "topicWeight": 0.0923076923076923}, {"docClass": "UK", "docId": "DB7281B3-1AB9-4BC3-A84B-B5393D782B11", "topicWeight": 0.0563380281690141}, {"docClass": "UK", "docId": "DBEB182E-5540-4C2B-8AA1-60C45B7690A3", "topicWeight": 0.015625}, {"docClass": "UK", "docId": "DBF4DEC5-051B-4CB2-B764-D200C1F19A5A", "topicWeight": 0.027027027027027}, {"docClass": "UK", "docId": "DC10B756-A366-4678-AD6A-1A4132EDC51F", "topicWeight": 0.0158730158730159}, {"docClass": "UK", "docId": "DCB2A336-A604-46C9-BE22-865C750B6D04", "topicWeight": 0.0271739130434783}, {"docClass": "UK", "docId": "DDF68DA1-D3AF-4BA6-A402-65FE50A01AE1", "topicWeight": 0.08}, {"docClass": "UK", "docId": "DF4CC0D3-7B1C-4A02-8872-2FB800C95A6D", "topicWeight": 0.0186335403726708}, {"docClass": "UK", "docId": "DF641F7B-2897-41E5-8A79-ACC4E5190FAD", "topicWeight": 0.0355029585798817}, {"docClass": "UK", "docId": "DFB3024C-F269-42F7-A51A-14E461243770", "topicWeight": 0.210526315789474}, {"docClass": "UK", "docId": "E009D7EB-0C9D-41E4-8456-A3F7D417E135", "topicWeight": 0.0740740740740741}, {"docClass": "UK", "docId": "E0AD3A66-5338-4AF3-A4BB-822736FCF18C", "topicWeight": 0.0285714285714286}, {"docClass": "UK", "docId": "E0B6AE5F-677B-4ADD-AEAB-2F54EEA3A7E6", "topicWeight": 0.0113636363636364}, {"docClass": "UK", "docId": "E112845B-2D49-4368-96D1-B7530F952C7B", "topicWeight": 0.0172413793103448}, {"docClass": "UK", "docId": "E19540C9-C637-4604-BDBB-32EF18A1E92A", "topicWeight": 0.0152671755725191}, {"docClass": "UK", "docId": "E197333B-E99C-4EE2-9895-9D0D2C90E765", "topicWeight": 0.00526315789473684}, {"docClass": "UK", "docId": "E19962C8-431B-4C58-BDB6-08DCA69942E4", "topicWeight": 0.0152284263959391}, {"docClass": "UK", "docId": "E1A4E4C2-1C0E-48B5-9D47-3211A1503CE8", "topicWeight": 0.0526315789473684}, {"docClass": "UK", "docId": "E1EC9EF3-FF6E-4121-82DF-4C887EBFEC30", "topicWeight": 1}, {"docClass": "UK", "docId": "E2653CA7-2A03-45AB-9115-673BC8867B74", "topicWeight": 0.0121951219512195}, {"docClass": "UK", "docId": "E2FFA61D-2C0B-4219-ABE5-74BEFB368615", "topicWeight": 0.0443037974683544}, {"docClass": "UK", "docId": "E340D3DF-FC62-4EDB-8B2B-A23DD49FB432", "topicWeight": 0.150943396226415}, {"docClass": "UK", "docId": "E3874E1F-5024-4ED5-8B49-8C6AFC52D48D", "topicWeight": 1}, {"docClass": "UK", "docId": "E3F40FFF-22CA-4217-B082-CE52F2D8E80D", "topicWeight": 0.194285714285714}, {"docClass": "UK", "docId": "E3FE9CE7-70B3-4328-B64F-14D18B1A61A4", "topicWeight": 0.00552486187845304}, {"docClass": "UK", "docId": "E42E0F56-BDFC-4F5C-8926-6FDB2A1ED833", "topicWeight": 0.0161290322580645}, {"docClass": "UK", "docId": "E49C65E5-4A02-4678-AA23-4A1F118820C2", "topicWeight": 0.357142857142857}, {"docClass": "UK", "docId": "E4B5F489-C2DD-4582-96BF-3410E409EE07", "topicWeight": 0.201680672268908}, {"docClass": "UK", "docId": "E5196C7A-094F-4339-9883-0F82C5A2A5A0", "topicWeight": 0.11304347826087}, {"docClass": "UK", "docId": "E52D371B-81F8-4806-A623-529CF96DC4A7", "topicWeight": 0.224043715846995}, {"docClass": "UK", "docId": "E552445A-57E0-4362-9BBA-9549987F3206", "topicWeight": 0.012987012987013}, {"docClass": "UK", "docId": "E5DE2138-9D93-4DDC-8CC7-0E3D5BF4672C", "topicWeight": 0.310606060606061}, {"docClass": "UK", "docId": "E63237CE-9FF2-40CF-B7AD-E3EC09188A75", "topicWeight": 0.00662251655629139}, {"docClass": "UK", "docId": "E6B3551E-87D9-4240-A6E2-C4220DDB9BBA", "topicWeight": 0.156424581005587}, {"docClass": "UK", "docId": "E6E7078E-6F45-4140-8093-F7B7EF50E479", "topicWeight": 0.00558659217877095}, {"docClass": "UK", "docId": "E719B4E6-C70E-4F12-B718-5E7D72762849", "topicWeight": 0.0150375939849624}, {"docClass": "UK", "docId": "E75CEC17-3DF0-4B6B-BE15-849AC0179499", "topicWeight": 0.182926829268293}, {"docClass": "UK", "docId": "E940184F-5D25-497E-AB4F-951D6BE98F94", "topicWeight": 0.0135135135135135}, {"docClass": "UK", "docId": "E944108C-CF66-4F63-808D-A25EBDE7A4E9", "topicWeight": 0.1}, {"docClass": "UK", "docId": "E95AC536-7798-40A0-88DC-D535555C75A7", "topicWeight": 0.0185185185185185}, {"docClass": "UK", "docId": "E9A940C2-BD1C-4E29-A4C2-D3897E0B8830", "topicWeight": 0.354838709677419}, {"docClass": "UK", "docId": "EA65D8EA-BCAC-473B-AE53-2D05D3A5D58C", "topicWeight": 0.0204081632653061}, {"docClass": "UK", "docId": "EAD2E4BD-E653-4F23-A57D-F89844120A62", "topicWeight": 0.0903225806451613}, {"docClass": "UK", "docId": "EB0BDCD4-1664-4442-863B-2490E7258A16", "topicWeight": 0.0414201183431953}, {"docClass": "UK", "docId": "EB147DB3-BB9E-4D81-ACA5-233051B2956B", "topicWeight": 0.168831168831169}, {"docClass": "UK", "docId": "EBA822B4-8FDF-4962-9EF7-70B7EE9E1D2E", "topicWeight": 0.0142857142857143}, {"docClass": "UK", "docId": "EC1CCFDC-849A-4DCE-AC97-286C508B996A", "topicWeight": 0.0403225806451613}, {"docClass": "UK", "docId": "EC66BDA7-2D1E-4319-A149-21FDAF92B726", "topicWeight": 0.00588235294117647}, {"docClass": "UK", "docId": "ECA0820D-CCE9-47D6-876D-75D447E0EE32", "topicWeight": 0.0568181818181818}, {"docClass": "UK", "docId": "ECB250D6-EE0B-41EC-AFC6-B6C06F9CF03C", "topicWeight": 0.0289855072463768}, {"docClass": "UK", "docId": "ECE4A7C5-98CA-4368-B3B3-F6F090E825E9", "topicWeight": 0.005}, {"docClass": "UK", "docId": "ECFC2555-284E-49DD-8CE5-EBB368CD5595", "topicWeight": 0.00884955752212389}, {"docClass": "UK", "docId": "EE0DFD9C-8447-43C0-BC8D-ACD730A71466", "topicWeight": 1}, {"docClass": "UK", "docId": "EE3200E8-B618-4303-9F49-1CD62FD46C65", "topicWeight": 0.0476190476190476}, {"docClass": "UK", "docId": "EE37CFC0-44CE-4277-AC86-59FE7B03709B", "topicWeight": 0.0158730158730159}, {"docClass": "UK", "docId": "F01F246D-BE0D-4BAF-BAA3-B3028D508D15", "topicWeight": 0.0654205607476635}, {"docClass": "UK", "docId": "F073B51A-6237-4494-A4D9-AB3772876A87", "topicWeight": 0.00735294117647059}, {"docClass": "UK", "docId": "F0DE4DE1-9A60-4D85-B926-6ED80125C4BB", "topicWeight": 0.148148148148148}, {"docClass": "UK", "docId": "F122A061-F042-4450-9AE8-D0366C12F0BB", "topicWeight": 0.543689320388349}, {"docClass": "UK", "docId": "F2CA0228-233A-41B2-8248-E88B7E57A466", "topicWeight": 0.0451127819548872}, {"docClass": "UK", "docId": "F2F990F7-3008-4FA9-9573-D8FD6C8EC9E4", "topicWeight": 0.26027397260274}, {"docClass": "UK", "docId": "F3281423-BD2F-46C4-A831-6E14ADC75971", "topicWeight": 0.0344827586206897}, {"docClass": "UK", "docId": "F38A420D-FE85-4472-810D-479DC7A2DE6A", "topicWeight": 0.0694444444444444}, {"docClass": "UK", "docId": "F4EA9F8C-20A4-43D4-A55C-51D0EDDDB6F7", "topicWeight": 0.0897435897435897}, {"docClass": "UK", "docId": "F5305BFF-1AFF-48CA-8B8E-2F1F69665F49", "topicWeight": 0.218543046357616}, {"docClass": "UK", "docId": "F54F9838-F5D3-451A-A4C6-631B2B753729", "topicWeight": 0.125}, {"docClass": "UK", "docId": "F5BF17F6-7EC1-4DA9-8345-D8F887D3DB83", "topicWeight": 0.455696202531646}, {"docClass": "UK", "docId": "F5D05F55-ED6A-48D5-8524-9894D27ECA2A", "topicWeight": 0.257425742574257}, {"docClass": "UK", "docId": "F774C0FA-C6B5-455D-AF72-D61A05E78D9A", "topicWeight": 0.204301075268817}, {"docClass": "UK", "docId": "F77605F5-95D6-4F0E-80CB-33A2CD4503DC", "topicWeight": 0.141304347826087}, {"docClass": "UK", "docId": "F7ADC697-A77E-44F2-8327-CD9A14433641", "topicWeight": 0.0714285714285714}, {"docClass": "UK", "docId": "F8A3F8C6-5C75-44BE-8BEC-1A8BBB5D7169", "topicWeight": 0.00892857142857143}, {"docClass": "UK", "docId": "F9960879-C4D4-4063-BEF1-47BF4FDD3E2D", "topicWeight": 0.371212121212121}, {"docClass": "UK", "docId": "F9BB00CA-4C49-458E-A0FD-048B018F6D72", "topicWeight": 0.189024390243902}, {"docClass": "UK", "docId": "FA8A1195-A7FC-4356-B919-5BDD08E77A92", "topicWeight": 0.0670391061452514}, {"docClass": "UK", "docId": "FB260AB9-26DE-4FD5-BBBB-332F76DE7BE0", "topicWeight": 0.0327868852459016}, {"docClass": "UK", "docId": "FBD0DC5A-6446-43C2-BFFE-ACFEF6258617", "topicWeight": 0.0216216216216216}, {"docClass": "UK", "docId": "FBDF36B6-34B4-42BA-887C-94B837F1C523", "topicWeight": 0.0657276995305164}, {"docClass": "UK", "docId": "FC4FF65E-A864-41AC-88AA-131631C55D7D", "topicWeight": 0.0214285714285714}, {"docClass": "UK", "docId": "FCB5F6C4-9BAD-4BEE-AC22-9B0824CAC417", "topicWeight": 0.0232558139534884}, {"docClass": "UK", "docId": "FCCFEE11-576F-40B6-8F41-E2DB2834D99D", "topicWeight": 0.140845070422535}, {"docClass": "UK", "docId": "FCF02371-67F9-4579-9B1A-85137FFC38ED", "topicWeight": 0.0740740740740741}, {"docClass": "UK", "docId": "FD5ED0F6-A7DC-4682-AF2B-112E7C566E38", "topicWeight": 0.0482758620689655}, {"docClass": "UK", "docId": "FD6D57C4-4958-4EC8-9B88-736D6DCC2927", "topicWeight": 0.0862068965517241}, {"docClass": "UK", "docId": "FD76EDF9-3B23-4A76-B6F9-B66FECF1031B", "topicWeight": 0.155038759689922}, {"docClass": "UK", "docId": "FE61F73F-EAB4-4635-86A1-E1C96F7DE2CB", "topicWeight": 0.0365296803652968}, {"docClass": "UK", "docId": "FEFC0FE5-684B-4C54-9A34-2A02EE269C59", "topicWeight": 0.12781954887218}, {"docClass": "UK", "docId": "FFE90A1D-FAEB-4C1E-9465-C4EBDF86859D", "topicWeight": 0.0210526315789474}, {"docClass": "EU-h", "docId": "193856", "topicWeight": 0.0752688172043011}, {"docClass": "EU-h", "docId": "193878", "topicWeight": 0.016260162601626}, {"docClass": "EU-h", "docId": "194160", "topicWeight": 0.00980392156862745}, {"docClass": "EU-h", "docId": "195171", "topicWeight": 0.018018018018018}, {"docClass": "EU-h", "docId": "195301", "topicWeight": 0.0108695652173913}, {"docClass": "EU-h", "docId": "195483", "topicWeight": 0.0103092783505155}, {"docClass": "EU-h", "docId": "195606", "topicWeight": 0.0434782608695652}, {"docClass": "EU-h", "docId": "196781", "topicWeight": 0.073394495412844}, {"docClass": "EU-h", "docId": "197242", "topicWeight": 0.00961538461538462}, {"docClass": "EU-h", "docId": "198456", "topicWeight": 0.159574468085106}, {"docClass": "EU-h", "docId": "199317", "topicWeight": 0.0103092783505155}, {"docClass": "EU-h", "docId": "200088", "topicWeight": 0.117647058823529}, {"docClass": "EU-h", "docId": "200150", "topicWeight": 0.172043010752688}, {"docClass": "EU-h", "docId": "200418", "topicWeight": 0.0444444444444444}, {"docClass": "EU-h", "docId": "201096", "topicWeight": 0.177777777777778}, {"docClass": "EU-h", "docId": "201284", "topicWeight": 0.0506329113924051}, {"docClass": "EU-h", "docId": "202462", "topicWeight": 0.0111111111111111}, {"docClass": "EU-h", "docId": "202919", "topicWeight": 0.032967032967033}, {"docClass": "EU-h", "docId": "203229", "topicWeight": 0.102564102564103}, {"docClass": "EU-h", "docId": "203549", "topicWeight": 0.0851063829787234}, {"docClass": "EU-h", "docId": "204760", "topicWeight": 0.00943396226415094}]